8BitALU/Algorithms.v
module Add(a, b, cin, cou, result);	//Add
	input[7:0]	 	a, b;
	input	 		cin;
	output[7:0] 	result;
	output 			cou;
	wire[8:0] 		sum;
	
	assign sum = a + b + cin;
	assign cou = sum[8];
	assign result = sum;
endmodule

module Sub(a, b, cou, result);		//Sub
	input[7:0]	a, b;
	output[7:0]	result;
	output		cou;
	
	reg			cou;
	
	always @ (a or b)
	begin
		if ( a > b )
			cou = 1;
		else
			cou = 0;
	end
	
	assign result = a - b;
endmodule

module Lm(a, cin, cou, result);		//LeftMove
	input[7:0]	a;
	input		cin;
	output[7:0]	result;
	output		cou;
	
	assign cou = a[7];
	assign result = (a<<1) + cin;
endmodule

module Rm(a, cin, cou, result);		//RightMove
	input[7:0]	a;
	input		cin;
	output[7:0]	result;
	output		cou;
	
	assign cou = a[0];
	assign result = (a>>1) + (cin<<7);
endmodule

module Lmt(a, result);				//LeftMove and Turn
	input[7:0]	a;
	output[7:0]	result;
	
	assign result = (a<<1) + (a[7]);
endmodule

module Rmt(a, result);				//RightMove and Turn
	input[7:0]	a;
	output[7:0]	result;
	
	assign result = (a>>1) + (a<<7);
endmodule

module Neg(a, result);				//result = !a
	input[7:0]	a;
	output[7:0]	result;
	assign result = ~a;
endmodule

module And(a, b, result);			//result = a and b
	input[7:0]	a, b;
	output[7:0]	result;
	assign result = a & b;
endmodule

module Or(a, b, result);			//result = a or b
	input[7:0]	a, b;
	output[7:0]	result;
	assign result = a | b;
endmodule

module Xor(a, b, result);			//result = a xor b
	input[7:0]	a, b;
	output[7:0]	result;
	assign result = a ^ b;
endmodule

8BitALU/ALU.v
module ALU(a, b, cin, cou, result, chooser); // ControlLogic
	input[15:0] 	chooser;

	input[7:0]	a, b;
	input 		cin;
	output[7:0] result;
	output 		cou;
	
	wire 		AddCou;		//Couts.
	wire 		SubCou;
	wire 		LmCou;
	wire		RmCou;
	
	wire[7:0] 	AddResult;	//Results.
	wire[7:0] 	SubResult;
	wire[7:0] 	LmResult;
	wire[7:0] 	RmResult;
	wire[7:0] 	LmtResult;
	wire[7:0] 	RmtResult;
	wire[7:0]	NegResult;
	wire[7:0]	AndResult;
	wire[7:0]	OrResult;
	wire[7:0]	XorResult;
	
	reg[7:0]	result;		//ALU result.
	reg			cou;		//ALU Cout.

	Add ALU_add (a, b, cin, AddCou, AddResult);	//Algorithms.
	Sub ALU_sub (a, b, SubCou, SubResult);
	Lm ALU_lm (a, cin, LmCou, LmResult);
	Rm ALU_rm (a, cin, RmCou, RmResult);
	Lmt ALU_lmt (a, LmtResult);
	Rmt ALU_rmt (a, RmtResult);
	Neg ALU_neg (a, NegResult);
	And ALU_and (a, b, AndResult);
	Or ALU_or (a, b, OrResult);
	Xor ALU_xor (a, b, XorResult);
	
	always @ (chooser or a or b or cin)		//Seclet Algorithms.
	begin
		if ( chooser == 16'b0000000000000001 ) 		// Add
			begin
				result = AddResult;
				cou = AddCou;
			end
		else if ( chooser == 16'b0000000000000010 )	// Sub
			begin
				result = SubResult;
				cou = SubCou;
			end
		else if ( chooser == 16'b0000000000000100 )	// LeftMove
			begin
				result = LmResult;
				cou = LmCou;
			end
		else if ( chooser == 16'b0000000000001000 )	// RightMove
			begin
				result = RmResult;
				cou = RmCou;
			end
		else if ( chooser == 16'b0000000000010000 )	// LeftMove and Turn
			begin
				result = LmtResult;
				cou = 0;
			end
		else if ( chooser == 16'b0000000000100000 )	// RightMove and Turn
			begin
				result = RmtResult;
				cou = 0;
			end
		else if ( chooser == 16'b0000000001000000 )	//Negation
			begin
				result = NegResult;
				cou = 0;
			end
		else if ( chooser == 16'b0000000010000000 )	//AND
			begin
				result = AndResult;
				cou = 0;
			end
		else if ( chooser == 16'b0000000100000000 )	//OR
			begin
				result = OrResult;
				cou = 0;
			end
		else if ( chooser == 16'b0000001000000000 )	//XOR
			begin
				result = XorResult;
				cou = 0;
			end
	end
endmodule

8BitALU/testbench.v
module testbench();
	reg[7:0]	a, b;
	reg			cin;
	reg[15:0]	chooser;
	wire[7:0] 	out;
	wire		cou;
	
	ALU ALU (a, b, cin, cou, out, chooser);
	
	initial
		begin
			#0 a=8'd0;	b=8'd0;	cin=1'b0; chooser=16'b0000000000000000;
			#5 a=8'd100;	b=8'd100;	cin=1'b0; chooser=16'b0000000000000001;//Add
			#5 a=8'd100;	b=8'd50; 	cin=1'b0; chooser=16'b0000000000000001;
			#5 a=8'd50;		b=8'd100; 	cin=1'b0; chooser=16'b0000000000000001;
			
			#5 a=8'd100;	b=8'd100;	cin=1'b0; chooser=16'b0000000000000010;//Sub
			#5 a=8'd100;	b=8'd50;	cin=1'b0; chooser=16'b0000000000000010;
			#5 a=8'd50;		b=8'd100;	cin=1'b0; chooser=16'b0000000000000010;
			
			#5 a=8'd100;	b=8'd0; 	cin=1'b0; chooser=16'b0000000000000100;//Lm
			#5 a=8'd50; 	b=8'd0;		cin=1'b0; chooser=16'b0000000000000100;
			#5 a=8'd129; 	b=8'd0;		cin=1'b0; chooser=16'b0000000000000100;
			#5 a=8'd100; 	b=8'd0; 	cin=1'b1; chooser=16'b0000000000000100;
			#5 a=8'd50; 	b=8'd0; 	cin=1'b1; chooser=16'b0000000000000100;
			#5 a=8'd129; 	b=8'd0; 	cin=1'b1; chooser=16'b0000000000000100;
			
			#5 a=8'd100;	b=8'd0; 	cin=1'b0; chooser=16'b0000000000001000;//Rm
			#5 a=8'd50; 	b=8'd0;		cin=1'b0; chooser=16'b0000000000001000;
			#5 a=8'd129; 	b=8'd0;		cin=1'b0; chooser=16'b0000000000001000;
			#5 a=8'd100; 	b=8'd0; 	cin=1'b1; chooser=16'b0000000000001000;
			#5 a=8'd50; 	b=8'd0; 	cin=1'b1; chooser=16'b0000000000001000;
			#5 a=8'd129; 	b=8'd0; 	cin=1'b1; chooser=16'b0000000000001000;
			
			#5 a=8'd100;	b=8'd0; 	cin=1'b0; chooser=16'b0000000000010000;//Lmt
			#5 a=8'd50; 	b=8'd0;		cin=1'b0; chooser=16'b0000000000010000;
			#5 a=8'd129; 	b=8'd0;		cin=1'b0; chooser=16'b0000000000010000;
			
			#5 a=8'd100;	b=8'd0; 	cin=1'b0; chooser=16'b0000000000100000;//Rmt
			#5 a=8'd50; 	b=8'd0;		cin=1'b0; chooser=16'b0000000000100000;
			#5 a=8'd129; 	b=8'd0;		cin=1'b0; chooser=16'b0000000000100000;
			
			#5 a=8'd85; 	b=8'd0;		cin=1'b0; chooser=16'b0000000001000000;//Neg  0101 0101
			#5 a=8'd170; 	b=8'd0;		cin=1'b0; chooser=16'b0000000001000000;		//1010 1010
			
			#5 a=8'd85; 	b=8'd211;	cin=1'b0; chooser=16'b0000000010000000;//AND  0101 0101 and 1101 0011
			#5 a=8'd170; 	b=8'd102;	cin=1'b0; chooser=16'b0000000010000000;		//1010 1010 and 0110 0110
			
			#5 a=8'd85; 	b=8'd211;	cin=1'b0; chooser=16'b0000000100000000;//OR   0101 0101 and 1101 0011
			#5 a=8'd170; 	b=8'd102;	cin=1'b0; chooser=16'b0000000100000000;		//1010 1010 and 0110 0110
			
			#5 a=8'd85; 	b=8'd211;	cin=1'b0; chooser=16'b0000001000000000;//XOR  0101 0101 and 1101 0011
			#5 a=8'd170; 	b=8'd102;	cin=1'b0; chooser=16'b0000001000000000;		//1010 1010 and 0110 0110
			
			#5 $finish;
		end

	initial
		$monitor("now chooser is %b, cin=%b ,a=%b, b=%b, result=%b, cou=%b", chooser, cin, a, b, out, cou);

	initial
		$dumpvars(0, testbench);
endmodule

8BitALU/dump.vcd
$date
	Sun Dec  2 15:12:19 2018
$end
$version
	Icarus Verilog
$end
$timescale
	1s
$end
$scope module testbench $end
$var wire 1 ! cou $end
$var wire 8 " out [7:0] $end
$var reg 8 # a [7:0] $end
$var reg 8 $ b [7:0] $end
$var reg 16 % chooser [15:0] $end
$var reg 1 & cin $end
$scope module ALU $end
$var wire 1 ' AddCou $end
$var wire 8 ( AddResult [7:0] $end
$var wire 8 ) AndResult [7:0] $end
$var wire 1 * LmCou $end
$var wire 8 + LmResult [7:0] $end
$var wire 8 , LmtResult [7:0] $end
$var wire 8 - NegResult [7:0] $end
$var wire 8 . OrResult [7:0] $end
$var wire 1 / RmCou $end
$var wire 8 0 RmResult [7:0] $end
$var wire 8 1 RmtResult [7:0] $end
$var wire 1 2 SubCou $end
$var wire 8 3 SubResult [7:0] $end
$var wire 8 4 XorResult [7:0] $end
$var wire 8 5 a [7:0] $end
$var wire 8 6 b [7:0] $end
$var wire 16 7 chooser [15:0] $end
$var wire 1 8 cin $end
$var reg 1 9 cou $end
$var reg 8 : result [7:0] $end
$scope module ALU_add $end
$var wire 8 ; a [7:0] $end
$var wire 8 < b [7:0] $end
$var wire 1 8 cin $end
$var wire 1 ' cou $end
$var wire 8 = result [7:0] $end
$var wire 9 > sum [8:0] $end
$upscope $end
$scope module ALU_sub $end
$var wire 8 ? a [7:0] $end
$var wire 8 @ b [7:0] $end
$var wire 8 A result [7:0] $end
$var reg 1 B cou $end
$upscope $end
$scope module ALU_lm $end
$var wire 8 C a [7:0] $end
$var wire 1 8 cin $end
$var wire 1 * cou $end
$var wire 8 D result [7:0] $end
$upscope $end
$scope module ALU_rm $end
$var wire 8 E a [7:0] $end
$var wire 1 8 cin $end
$var wire 1 / cou $end
$var wire 8 F result [7:0] $end
$upscope $end
$scope module ALU_lmt $end
$var wire 8 G a [7:0] $end
$var wire 8 H result [7:0] $end
$upscope $end
$scope module ALU_rmt $end
$var wire 8 I a [7:0] $end
$var wire 8 J result [7:0] $end
$upscope $end
$scope module ALU_neg $end
$var wire 8 K a [7:0] $end
$var wire 8 L result [7:0] $end
$upscope $end
$scope module ALU_and $end
$var wire 8 M a [7:0] $end
$var wire 8 N b [7:0] $end
$var wire 8 O result [7:0] $end
$upscope $end
$scope module ALU_or $end
$var wire 8 P a [7:0] $end
$var wire 8 Q b [7:0] $end
$var wire 8 R result [7:0] $end
$upscope $end
$scope module ALU_xor $end
$var wire 8 S a [7:0] $end
$var wire 8 T b [7:0] $end
$var wire 8 U result [7:0] $end
$upscope $end
$upscope $end
$upscope $end
$enddefinitions $end
#0
$dumpvars
b0 U
b0 T
b0 S
b0 R
b0 Q
b0 P
b0 O
b0 N
b0 M
b11111111 L
b0 K
b0 J
b0 I
b0 H
b0 G
b0 F
b0 E
b0 D
b0 C
0B
b0 A
b0 @
b0 ?
b0 >
b0 =
b0 <
b0 ;
bx :
x9
08
b0 7
b0 6
b0 5
b0 4
b0 3
02
b0 1
b0 0
0/
b0 .
b11111111 -
b0 ,
b0 +
0*
b0 )
b0 (
0'
0&
b0 %
b0 $
b0 #
bx "
x!
$end
#5
09
0!
b11001000 :
b11001000 "
b11001000 (
b11001000 =
b11001000 +
b11001000 D
b110010 0
b110010 F
b11001000 ,
b11001000 H
b110010 1
b110010 J
b10011011 -
b10011011 L
b1100100 )
b1100100 O
b1100100 .
b1100100 R
b1 %
b1 7
b1100100 $
b1100100 6
b1100100 <
b1100100 @
b1100100 N
b1100100 Q
b1100100 T
b1100100 #
b1100100 5
b1100100 ;
b1100100 ?
b1100100 C
b1100100 E
b1100100 G
b1100100 I
b1100100 K
b1100100 M
b1100100 P
b1100100 S
b11001000 >
b0 3
b0 A
#10
1B
12
b10010110 :
b10010110 "
b10010110 (
b10010110 =
b100000 )
b100000 O
b1110110 .
b1110110 R
b1010110 4
b1010110 U
b110010 $
b110010 6
b110010 <
b110010 @
b110010 N
b110010 Q
b110010 T
b10010110 >
b110010 3
b110010 A
#15
0B
02
b1100100 +
b1100100 D
b11001 0
b11001 F
b1100100 ,
b1100100 H
b11001 1
b11001 J
b11001101 -
b11001101 L
b1100100 $
b1100100 6
b1100100 <
b1100100 @
b1100100 N
b1100100 Q
b1100100 T
b110010 #
b110010 5
b110010 ;
b110010 ?
b110010 C
b110010 E
b110010 G
b110010 I
b110010 K
b110010 M
b110010 P
b110010 S
b10010110 >
b11001110 3
b11001110 A
#20
b0 :
b0 "
b11001000 (
b11001000 =
b11001000 +
b11001000 D
b110010 0
b110010 F
b11001000 ,
b11001000 H
b110010 1
b110010 J
b10011011 -
b10011011 L
b1100100 )
b1100100 O
b1100100 .
b1100100 R
b0 4
b0 U
b10 %
b10 7
b1100100 #
b1100100 5
b1100100 ;
b1100100 ?
b1100100 C
b1100100 E
b1100100 G
b1100100 I
b1100100 K
b1100100 M
b1100100 P
b1100100 S
b11001000 >
b0 3
b0 A
#25
1B
12
b110010 :
b110010 "
b10010110 (
b10010110 =
b100000 )
b100000 O
b1110110 .
b1110110 R
b1010110 4
b1010110 U
b110010 $
b110010 6
b110010 <
b110010 @
b110010 N
b110010 Q
b110010 T
b10010110 >
b110010 3
b110010 A
#30
0B
02
19
1!
b11001110 :
b11001110 "
b1100100 +
b1100100 D
b11001 0
b11001 F
b1100100 ,
b1100100 H
b11001 1
b11001 J
b11001101 -
b11001101 L
b1100100 $
b1100100 6
b1100100 <
b1100100 @
b1100100 N
b1100100 Q
b1100100 T
b110010 #
b110010 5
b110010 ;
b110010 ?
b110010 C
b110010 E
b110010 G
b110010 I
b110010 K
b110010 M
b110010 P
b110010 S
b10010110 >
b11001110 3
b11001110 A
#35
1B
12
09
0!
b11001000 :
b11001000 "
b1100100 (
b1100100 =
b11001000 +
b11001000 D
b110010 0
b110010 F
b11001000 ,
b11001000 H
b110010 1
b110010 J
b10011011 -
b10011011 L
b0 )
b0 O
b1100100 .
b1100100 R
b1100100 4
b1100100 U
b100 %
b100 7
b0 $
b0 6
b0 <
b0 @
b0 N
b0 Q
b0 T
b1100100 #
b1100100 5
b1100100 ;
b1100100 ?
b1100100 C
b1100100 E
b1100100 G
b1100100 I
b1100100 K
b1100100 M
b1100100 P
b1100100 S
b1100100 >
b1100100 3
b1100100 A
#40
b1100100 :
b1100100 "
b110010 (
b110010 =
b1100100 +
b1100100 D
b11001 0
b11001 F
b1100100 ,
b1100100 H
b11001 1
b11001 J
b11001101 -
b11001101 L
b110010 .
b110010 R
b110010 4
b110010 U
b110010 #
b110010 5
b110010 ;
b110010 ?
b110010 C
b110010 E
b110010 G
b110010 I
b110010 K
b110010 M
b110010 P
b110010 S
b110010 >
b110010 3
b110010 A
#45
19
1!
b10 :
b10 "
b10000001 (
b10000001 =
1*
b10 +
b10 D
1/
b1000000 0
b1000000 F
b11 ,
b11 H
b11000000 1
b11000000 J
b1111110 -
b1111110 L
b10000001 .
b10000001 R
b10000001 4
b10000001 U
b10000001 #
b10000001 5
b10000001 ;
b10000001 ?
b10000001 C
b10000001 E
b10000001 G
b10000001 I
b10000001 K
b10000001 M
b10000001 P
b10000001 S
b10000001 >
b10000001 3
b10000001 A
#50
09
0!
b11001001 :
b11001001 "
b1100101 (
b1100101 =
0*
0/
b10110010 0
b10110010 F
b11001000 ,
b11001000 H
b110010 1
b110010 J
b10011011 -
b10011011 L
b1100100 .
b1100100 R
b1100100 4
b1100100 U
1&
18
b11001001 +
b11001001 D
b1100100 #
b1100100 5
b1100100 ;
b1100100 ?
b1100100 C
b1100100 E
b1100100 G
b1100100 I
b1100100 K
b1100100 M
b1100100 P
b1100100 S
b1100101 >
b1100100 3
b1100100 A
#55
b1100101 :
b1100101 "
b110011 (
b110011 =
b1100101 +
b1100101 D
b10011001 0
b10011001 F
b1100100 ,
b1100100 H
b11001 1
b11001 J
b11001101 -
b11001101 L
b110010 .
b110010 R
b110010 4
b110010 U
b110010 #
b110010 5
b110010 ;
b110010 ?
b110010 C
b110010 E
b110010 G
b110010 I
b110010 K
b110010 M
b110010 P
b110010 S
b110011 >
b110010 3
b110010 A
#60
19
1!
b11 :
b11 "
b10000010 (
b10000010 =
1*
b11 +
b11 D
1/
b11000000 0
b11000000 F
b11 ,
b11 H
b11000000 1
b11000000 J
b1111110 -
b1111110 L
b10000001 .
b10000001 R
b10000001 4
b10000001 U
b10000001 #
b10000001 5
b10000001 ;
b10000001 ?
b10000001 C
b10000001 E
b10000001 G
b10000001 I
b10000001 K
b10000001 M
b10000001 P
b10000001 S
b10000010 >
b10000001 3
b10000001 A
#65
09
0!
b10110010 :
b10110010 "
b1100100 (
b1100100 =
0*
0/
b110010 0
b110010 F
b11001000 ,
b11001000 H
b110010 1
b110010 J
b10011011 -
b10011011 L
b1100100 .
b1100100 R
b1100100 4
b1100100 U
b1000 %
b1000 7
0&
08
b11001000 +
b11001000 D
b1100100 #
b1100100 5
b1100100 ;
b1100100 ?
b1100100 C
b1100100 E
b1100100 G
b1100100 I
b1100100 K
b1100100 M
b1100100 P
b1100100 S
b1100100 >
b1100100 3
b1100100 A
#70
b11001 :
b11001 "
b110010 (
b110010 =
b1100100 +
b1100100 D
b11001 0
b11001 F
b1100100 ,
b1100100 H
b11001 1
b11001 J
b11001101 -
b11001101 L
b110010 .
b110010 R
b110010 4
b110010 U
b110010 #
b110010 5
b110010 ;
b110010 ?
b110010 C
b110010 E
b110010 G
b110010 I
b110010 K
b110010 M
b110010 P
b110010 S
b110010 >
b110010 3
b110010 A
#75
19
1!
b1000000 :
b1000000 "
b10000001 (
b10000001 =
1*
b10 +
b10 D
1/
b1000000 0
b1000000 F
b11 ,
b11 H
b11000000 1
b11000000 J
b1111110 -
b1111110 L
b10000001 .
b10000001 R
b10000001 4
b10000001 U
b10000001 #
b10000001 5
b10000001 ;
b10000001 ?
b10000001 C
b10000001 E
b10000001 G
b10000001 I
b10000001 K
b10000001 M
b10000001 P
b10000001 S
b10000001 >
b10000001 3
b10000001 A
#80
09
0!
b110010 :
b110010 "
b1100101 (
b1100101 =
0*
0/
b10110010 0
b10110010 F
b11001000 ,
b11001000 H
b110010 1
b110010 J
b10011011 -
b10011011 L
b1100100 .
b1100100 R
b1100100 4
b1100100 U
1&
18
b11001001 +
b11001001 D
b1100100 #
b1100100 5
b1100100 ;
b1100100 ?
b1100100 C
b1100100 E
b1100100 G
b1100100 I
b1100100 K
b1100100 M
b1100100 P
b1100100 S
b1100101 >
b1100100 3
b1100100 A
#85
b10011001 :
b10011001 "
b110011 (
b110011 =
b1100101 +
b1100101 D
b10011001 0
b10011001 F
b1100100 ,
b1100100 H
b11001 1
b11001 J
b11001101 -
b11001101 L
b110010 .
b110010 R
b110010 4
b110010 U
b110010 #
b110010 5
b110010 ;
b110010 ?
b110010 C
b110010 E
b110010 G
b110010 I
b110010 K
b110010 M
b110010 P
b110010 S
b110011 >
b110010 3
b110010 A
#90
19
1!
b11000000 :
b11000000 "
b10000010 (
b10000010 =
1*
b11 +
b11 D
1/
b11000000 0
b11000000 F
b11 ,
b11 H
b11000000 1
b11000000 J
b1111110 -
b1111110 L
b10000001 .
b10000001 R
b10000001 4
b10000001 U
b10000001 #
b10000001 5
b10000001 ;
b10000001 ?
b10000001 C
b10000001 E
b10000001 G
b10000001 I
b10000001 K
b10000001 M
b10000001 P
b10000001 S
b10000010 >
b10000001 3
b10000001 A
#95
09
0!
b11001000 :
b11001000 "
b1100100 (
b1100100 =
0*
0/
b110010 0
b110010 F
b11001000 ,
b11001000 H
b110010 1
b110010 J
b10011011 -
b10011011 L
b1100100 .
b1100100 R
b1100100 4
b1100100 U
b10000 %
b10000 7
0&
08
b11001000 +
b11001000 D
b1100100 #
b1100100 5
b1100100 ;
b1100100 ?
b1100100 C
b1100100 E
b1100100 G
b1100100 I
b1100100 K
b1100100 M
b1100100 P
b1100100 S
b1100100 >
b1100100 3
b1100100 A
#100
b1100100 :
b1100100 "
b110010 (
b110010 =
b1100100 +
b1100100 D
b11001 0
b11001 F
b1100100 ,
b1100100 H
b11001 1
b11001 J
b11001101 -
b11001101 L
b110010 .
b110010 R
b110010 4
b110010 U
b110010 #
b110010 5
b110010 ;
b110010 ?
b110010 C
b110010 E
b110010 G
b110010 I
b110010 K
b110010 M
b110010 P
b110010 S
b110010 >
b110010 3
b110010 A
#105
b11 :
b11 "
b10000001 (
b10000001 =
1*
b10 +
b10 D
1/
b1000000 0
b1000000 F
b11 ,
b11 H
b11000000 1
b11000000 J
b1111110 -
b1111110 L
b10000001 .
b10000001 R
b10000001 4
b10000001 U
b10000001 #
b10000001 5
b10000001 ;
b10000001 ?
b10000001 C
b10000001 E
b10000001 G
b10000001 I
b10000001 K
b10000001 M
b10000001 P
b10000001 S
b10000001 >
b10000001 3
b10000001 A
#110
b110010 :
b110010 "
b1100100 (
b1100100 =
0*
b11001000 +
b11001000 D
0/
b110010 0
b110010 F
b11001000 ,
b11001000 H
b110010 1
b110010 J
b10011011 -
b10011011 L
b1100100 .
b1100100 R
b1100100 4
b1100100 U
b100000 %
b100000 7
b1100100 #
b1100100 5
b1100100 ;
b1100100 ?
b1100100 C
b1100100 E
b1100100 G
b1100100 I
b1100100 K
b1100100 M
b1100100 P
b1100100 S
b1100100 >
b1100100 3
b1100100 A
#115
b11001 :
b11001 "
b110010 (
b110010 =
b1100100 +
b1100100 D
b11001 0
b11001 F
b1100100 ,
b1100100 H
b11001 1
b11001 J
b11001101 -
b11001101 L
b110010 .
b110010 R
b110010 4
b110010 U
b110010 #
b110010 5
b110010 ;
b110010 ?
b110010 C
b110010 E
b110010 G
b110010 I
b110010 K
b110010 M
b110010 P
b110010 S
b110010 >
b110010 3
b110010 A
#120
b11000000 :
b11000000 "
b10000001 (
b10000001 =
1*
b10 +
b10 D
1/
b1000000 0
b1000000 F
b11 ,
b11 H
b11000000 1
b11000000 J
b1111110 -
b1111110 L
b10000001 .
b10000001 R
b10000001 4
b10000001 U
b10000001 #
b10000001 5
b10000001 ;
b10000001 ?
b10000001 C
b10000001 E
b10000001 G
b10000001 I
b10000001 K
b10000001 M
b10000001 P
b10000001 S
b10000001 >
b10000001 3
b10000001 A
#125
b10101010 :
b10101010 "
b1010101 (
b1010101 =
0*
b10101010 +
b10101010 D
b101010 0
b101010 F
b10101010 ,
b10101010 H
b10101010 1
b10101010 J
b10101010 -
b10101010 L
b1010101 .
b1010101 R
b1010101 4
b1010101 U
b1000000 %
b1000000 7
b1010101 #
b1010101 5
b1010101 ;
b1010101 ?
b1010101 C
b1010101 E
b1010101 G
b1010101 I
b1010101 K
b1010101 M
b1010101 P
b1010101 S
b1010101 >
b1010101 3
b1010101 A
#130
b1010101 :
b1010101 "
b10101010 (
b10101010 =
1*
b1010100 +
b1010100 D
0/
b1010101 0
b1010101 F
b1010101 ,
b1010101 H
b1010101 1
b1010101 J
b1010101 -
b1010101 L
b10101010 .
b10101010 R
b10101010 4
b10101010 U
b10101010 #
b10101010 5
b10101010 ;
b10101010 ?
b10101010 C
b10101010 E
b10101010 G
b10101010 I
b10101010 K
b10101010 M
b10101010 P
b10101010 S
b10101010 >
b10101010 3
b10101010 A
#135
1'
0B
02
b1010001 :
b1010001 "
b101000 (
b101000 =
0*
b10101010 +
b10101010 D
1/
b101010 0
b101010 F
b10101010 ,
b10101010 H
b10101010 1
b10101010 J
b10101010 -
b10101010 L
b1010001 )
b1010001 O
b11010111 .
b11010111 R
b10000110 4
b10000110 U
b10000000 %
b10000000 7
b11010011 $
b11010011 6
b11010011 <
b11010011 @
b11010011 N
b11010011 Q
b11010011 T
b1010101 #
b1010101 5
b1010101 ;
b1010101 ?
b1010101 C
b1010101 E
b1010101 G
b1010101 I
b1010101 K
b1010101 M
b1010101 P
b1010101 S
b100101000 >
b10000010 3
b10000010 A
#140
1B
12
b100010 :
b100010 "
b10000 (
b10000 =
1*
b1010100 +
b1010100 D
0/
b1010101 0
b1010101 F
b1010101 ,
b1010101 H
b1010101 1
b1010101 J
b1010101 -
b1010101 L
b100010 )
b100010 O
b11101110 .
b11101110 R
b11001100 4
b11001100 U
b1100110 $
b1100110 6
b1100110 <
b1100110 @
b1100110 N
b1100110 Q
b1100110 T
b10101010 #
b10101010 5
b10101010 ;
b10101010 ?
b10101010 C
b10101010 E
b10101010 G
b10101010 I
b10101010 K
b10101010 M
b10101010 P
b10101010 S
b100010000 >
b1000100 3
b1000100 A
#145
0B
02
b11010111 :
b11010111 "
b101000 (
b101000 =
0*
b10101010 +
b10101010 D
1/
b101010 0
b101010 F
b10101010 ,
b10101010 H
b10101010 1
b10101010 J
b10101010 -
b10101010 L
b1010001 )
b1010001 O
b11010111 .
b11010111 R
b10000110 4
b10000110 U
b100000000 %
b100000000 7
b11010011 $
b11010011 6
b11010011 <
b11010011 @
b11010011 N
b11010011 Q
b11010011 T
b1010101 #
b1010101 5
b1010101 ;
b1010101 ?
b1010101 C
b1010101 E
b1010101 G
b1010101 I
b1010101 K
b1010101 M
b1010101 P
b1010101 S
b100101000 >
b10000010 3
b10000010 A
#150
1B
12
b11101110 :
b11101110 "
b10000 (
b10000 =
1*
b1010100 +
b1010100 D
0/
b1010101 0
b1010101 F
b1010101 ,
b1010101 H
b1010101 1
b1010101 J
b1010101 -
b1010101 L
b100010 )
b100010 O
b11101110 .
b11101110 R
b11001100 4
b11001100 U
b1100110 $
b1100110 6
b1100110 <
b1100110 @
b1100110 N
b1100110 Q
b1100110 T
b10101010 #
b10101010 5
b10101010 ;
b10101010 ?
b10101010 C
b10101010 E
b10101010 G
b10101010 I
b10101010 K
b10101010 M
b10101010 P
b10101010 S
b100010000 >
b1000100 3
b1000100 A
#155
0B
02
b10000110 :
b10000110 "
b101000 (
b101000 =
0*
b10101010 +
b10101010 D
1/
b101010 0
b101010 F
b10101010 ,
b10101010 H
b10101010 1
b10101010 J
b10101010 -
b10101010 L
b1010001 )
b1010001 O
b11010111 .
b11010111 R
b10000110 4
b10000110 U
b1000000000 %
b1000000000 7
b11010011 $
b11010011 6
b11010011 <
b11010011 @
b11010011 N
b11010011 Q
b11010011 T
b1010101 #
b1010101 5
b1010101 ;
b1010101 ?
b1010101 C
b1010101 E
b1010101 G
b1010101 I
b1010101 K
b1010101 M
b1010101 P
b1010101 S
b100101000 >
b10000010 3
b10000010 A
#160
1B
12
b11001100 :
b11001100 "
b10000 (
b10000 =
1*
b1010100 +
b1010100 D
0/
b1010101 0
b1010101 F
b1010101 ,
b1010101 H
b1010101 1
b1010101 J
b1010101 -
b1010101 L
b100010 )
b100010 O
b11101110 .
b11101110 R
b11001100 4
b11001100 U
b1100110 $
b1100110 6
b1100110 <
b1100110 @
b1100110 N
b1100110 Q
b1100110 T
b10101010 #
b10101010 5
b10101010 ;
b10101010 ?
b10101010 C
b10101010 E
b10101010 G
b10101010 I
b10101010 K
b10101010 M
b10101010 P
b10101010 S
b100010000 >
b1000100 3
b1000100 A
